vexstorage/__init__.py
vexstorage/__main__.py
vexstorage/database.py
vexstorage-0.4.0.dist-info/DESCRIPTION.rst
vexstorage-0.4.0.dist-info/METADATA
vexstorage-0.4.0.dist-info/RECORD
vexstorage-0.4.0.dist-info/WHEEL
vexstorage-0.4.0.dist-info/entry_points.txt
vexstorage-0.4.0.dist-info/metadata.json
vexstorage-0.4.0.dist-info/top_level.txt
