Metadata-Version: 2.0
Name: vexstorage
Version: 0.4.0
Summary: Database storage for vexbot
Home-page: https://github.com/benhoff/vexstorage
Author: Ben Hoff
Author-email: beohoff@gmail.com
License: GPL3
Keywords: vexbot
Platform: UNKNOWN
Classifier: Development Status :: 1 - Planning
Classifier: Intended Audience :: Developers
Classifier: License :: OSI Approved :: GNU General Public License v3 (GPLv3)
Classifier: Programming Language :: Python :: 3
Classifier: Programming Language :: Python :: 3.5
Classifier: Topic :: Utilities
Classifier: Operating System :: OS Independent
Requires-Dist: pyzmq
Requires-Dist: sqlalchemy
Requires-Dist: vexmessage
Provides-Extra: dev
Requires-Dist: flake8; extra == 'dev'
